vikor_ufpe/__init__.py
vikor_ufpe/decision.py
vikor_ufpe/exceptions.py
vikor_ufpe/main.py
vikor_ufpe/models.py
vikor_ufpe/utils.py
vikor_ufpe-0.1.2.dist-info/LICENCE
vikor_ufpe-0.1.2.dist-info/METADATA
vikor_ufpe-0.1.2.dist-info/WHEEL
vikor_ufpe-0.1.2.dist-info/RECORD
