Metadata-Version: 2.3
Name: vikor_ufpe
Version: 0.1.2
Summary: Biblioteca Vikor
License: MIT
Author: Gustavo Silva, Arlen Filho, Hyan Silva, Eraldo Cassimiro
Requires-Python: >=3.10
Classifier: License :: OSI Approved :: MIT License
Classifier: Programming Language :: Python :: 3
Classifier: Programming Language :: Python :: 3.10
Classifier: Programming Language :: Python :: 3.11
Classifier: Programming Language :: Python :: 3.12
Classifier: Programming Language :: Python :: 3.13
